cglbtrial/__init__.py
cglbtrial/conversion.py
cglbtrial-0.10.0.dist-info/METADATA
cglbtrial-0.10.0.dist-info/WHEEL
cglbtrial-0.10.0.dist-info/RECORD
