Metadata-Version: 2.1
Name: cglbtrial
Version: 0.10.0
Summary: cglbtrial is a cglb trial
Home-page: https://cesgenslab.cloud/
Author: CesGensLaB
Author-email: contact@cesgenlab.fr
Requires-Python: >=3.12,<4.0
Classifier: Programming Language :: Python :: 3
Classifier: Programming Language :: Python :: 3.12
Requires-Dist: jinja2 (>=3.1.4,<4.0.0)
